{
  "state": "VIC",
  "suburb": "Buffalo River",
  "gender": {
    "Male": 259,
    "Female": 228
  },
  "age": {
    "0 - 4 years": 19,
    "5 - 14 years": 70,
    "15 - 19 years": 40,
    "20 - 24 years": 14,
    "25 - 34 years": 21,
    "35 - 44 years": 65,
    "45 - 54 years": 94,
    "55 - 64 years": 96,
    "65 - 74 years": 53,
    "75 - 84 years": 14,
    "85 years and over": 0
  },
  "school_completed": {
    "Year 12 or equivalent": 145,
    "Year 11 or equivalent": 74,
    "Year 10 or equivalent": 79,
    "Year 9 or equivalent": 39,
    "Year 8 or below": 31,
    "Did not go to school": 3
  },
  "marital_status": {
    "Married": 228,
    "Separated": 6,
    "Divorced": 32,
    "Widowed": 18,
    "Never Married": 114
  },
  "country_of_birth": {
    "Australia": 411,
    "Bosnia and Herzegovina": 0,
    "Cambodia": 0,
    "Canada": 0,
    "China": 0,
    "Croatia": 7,
    "Egypt": 0,
    "Fiji": 0,
    "Germany": 0,
    "Greece": 0,
    "Hong Kong": 0,
    "India": 0,
    "Indonesia": 0,
    "Iraq": 0,
    "Ireland": 0,
    "Italy": 14,
    "South Korea": 0,
    "Lebanon": 0,
    "Malaysia": 0,
    "Malta": 0,
    "Netherlands": 3,
    "New Zealand": 6,
    "Philippines": 0,
    "Poland": 0,
    "Singapore": 0,
    "South Africa": 0,
    "South Eastern Europe": 4,
    "Sri Lanka": 0,
    "Thailand": 0,
    "Turkey": 0,
    "United Kingdom": 17,
    "United States of America": 0,
    "Vietnam": 0,
    "Elsewhere": 8
  },
  "languages_spoken": {
    "English": 420,
    "Arabic": 0,
    "Assyrian": 0,
    "Australian Indigenous Languages": 0,
    "Cantonese": 0,
    "Mandarin": 0,
    "Other Chinese": 0,
    "Croatian": 6,
    "Dutch": 0,
    "French": 0,
    "German": 0,
    "Greek": 0,
    "Hungarian": 0,
    "Bengali": 0,
    "Hindi": 0,
    "Punjabi": 0,
    "Sinhalese": 0,
    "Urdu": 0,
    "Other Indo Aryan": 0,
    "Dari": 0,
    "Persian": 0,
    "Other Iranic": 0,
    "Italian": 33,
    "Japanese": 0,
    "Khmer": 0,
    "Korean": 0,
    "Macedonian": 0,
    "Maltese": 0,
    "Polish": 0,
    "Portuguese": 0,
    "Russian": 3,
    "Samoan": 0,
    "Serbian": 0,
    "Filipino": 0,
    "Indonesian": 0,
    "Tagalog": 0,
    "Other Southeast Asian": 0,
    "Spanish": 0,
    "Tamil": 0,
    "Thai": 0,
    "Turkish": 0,
    "Vietnamese": 0,
    "Other": 6
  },
  "religion": {
    "Buddhism": 6,
    "Anglican": 79,
    "Assyrian Apostolic": 0,
    "Baptist": 3,
    "Brethren": 0,
    "Catholic": 184,
    "Churches of Christ": 3,
    "Eastern Orthodox": 6,
    "Jehovahs Witnesses": 6,
    "Latter day Saints": 0,
    "Lutheran": 3,
    "Oriental Orthodox": 0,
    "Other Protestant": 0,
    "Pentecostal": 0,
    "Presbyterian and Reformed": 15,
    "Salvation Army": 3,
    "Seventh day Adventist": 0,
    "Uniting Church": 52,
    "Other Christian": 16,
    "Hinduism": 0,
    "Islam": 0,
    "Judaism": 0,
    "Australian Aboriginal Traditional Religions": 0,
    "Other religious groups": 0,
    "No Religion": 78
  },
  "weekly_personal_income": {
    "No Income": 29,
    "$1 - $199": 41,
    "$200 - $299": 66,
    "$300 - $399": 36,
    "$400 - $599": 34,
    "$600 - $799": 47,
    "$800 - $999": 44,
    "$1000 - $1249": 30,
    "$1250 - $1499": 15,
    "$1500 - $1999": 16,
    "$2000 or more": 13
  },
  "number_of_children": {
    "No children": 39,
    "One child": 8,
    "Two children": 53,
    "Three children": 44,
    "Four children": 20,
    "Five children": 6,
    "Six or more children": 3
  },
  "weekly_household_income": {
    "$1 - $199": 4,
    "$200 - $299": 9,
    "$300 - $399": 11,
    "$400 - $599": 22,
    "$600 - $799": 20,
    "$800 - $999": 12,
    "$1000 - $1249": 13,
    "$1250 - $1499": 10,
    "$1500 - $1999": 17,
    "$2000 - $2499": 19,
    "$2500 - $2999": 10,
    "$3000 - $3499": 6,
    "$3500 - $3999": 0,
    "4000 or more": 5
  },
  "vehicles_per_house": {
    "No motor vehicles": 9,
    "One motor vehicle": 45,
    "Two motor vehicles": 81,
    "Three motor vehicles": 34,
    "Four or more motor vehicles": 9
  },
  "monthly_mortgage_repayment": {
    "$0 - $299": 4,
    "$300 - $449": 4,
    "$450 - $599": 4,
    "$600 - $799": 6,
    "$800 - $999": 5,
    "$1000 - $1399": 7,
    "$1400 - $1799": 11,
    "$1800 - $2399": 4,
    "$2400 - $2999": 10,
    "$3000 - $3999": 4,
    "$4000 and over": 0
  },
  "weekly_rent": {
    "$0 - $74": 8,
    "$75 - $99": 3,
    "$100 - $149": 10,
    "$150 - $199": 8,
    "$200 - $224": 3,
    "$225 - $274": 3,
    "$275 - $349": 0,
    "$350 - $449": 0,
    "$450 - $549": 0,
    "$550 - $649": 0,
    "$650 and over": 0
  },
  "internet_type": {
    "None": 46,
    "Broadband": 119,
    "Dial up": 5,
    "Other": 3
  },
  "level_of_education": {
    "Postgraduate Degree": 6,
    "Graduate Diploma and Graduate Certificate": 17,
    "Bachelor Degree": 35,
    "Advanced Diploma and Diploma": 31,
    "Other Certificate": 6,
    "Certificate III and IV": 72,
    "Certificate I and II": 0
  },
  "qualifications": {
    "Natural and Physical Sciences": 3,
    "Information Technology": 3,
    "Engineering and Related Technologies": 43,
    "Architecture and Building": 13,
    "Agriculture Environmental and Related Studies": 12,
    "Health": 28,
    "Education": 23,
    "Management and Commerce": 26,
    "Society and Culture": 8,
    "Creative Arts": 8,
    "Food Hospitality and Personal Services": 9,
    "Mixed Field Programmes": 0
  },
  "industry_of_employment": {
    "Agriculture forestry and fishing": 30,
    "Mining": 0,
    "Manufacturing": 37,
    "Electricity gas water and waste services": 6,
    "Construction": 10,
    "Wholesale trade": 4,
    "Retail trade": 28,
    "Accommodation and food services": 7,
    "Transport postal and warehousing": 9,
    "Information media and telecommunications": 0,
    "Financial and insurance services": 3,
    "Rental hiring and real estate services": 0,
    "Professional scientific and technical services": 7,
    "Administrative and support services": 7,
    "Public administration and safety": 16,
    "Education and training": 25,
    "Health care and social assistance": 34,
    "Arts and recreation services": 0
  },
  "occupation": {
    "Manager": 41,
    "Professional": 49,
    "Technician / Trade": 36,
    "Community / Personal Service": 26,
    "Clerical / Administrative": 17,
    "Sales": 14,
    "Machinery Operator / Driver": 20,
    "Labourer": 24
  },
  "travel_to_work": {
    "Train": 0,
    "Bus": 0,
    "Ferry": 0,
    "Tram": 0,
    "Taxi": 0,
    "Car as driver": 161,
    "Car as passenger": 11,
    "Truck": 4,
    "Motorbike scooter": 0,
    "Bicycle": 0,
    "Other": 0,
    "Walked only": 8,
    "Train and Bus": 0,
    "Train and Ferry": 0,
    "Train and Tram": 0,
    "Train and Car as driver": 0,
    "Train and Car as passenger": 0,
    "Train and Other": 0,
    "Bus and Ferry": 0,
    "Bus and Tram": 0,
    "Bus and Car as driver": 0,
    "Bus and Car as passenger": 0,
    "Bus and Other": 0,
    "Other two methods": 3,
    "Train and two other methods": 0,
    "Bus and two other methods excludes train": 0,
    "Other three methods": 0,
    "Worked at home": 17,
    "Did not go to work": 22
  },
  "license": "Creative Commons Attribution 2.5 Australia",
  "attribution": "Based on Australian Bureau of Statistics Data",
  "year": "2011",
  "spatial": {
    "pole": [
      -36.92008044306482,
      146.82113703433436
    ],
    "area": 144481.47879662318,
    "poly": "nd~~Eixi_[kAbSmIw@MYcRqBx@oNaKcAfBi]EwAgAW{BwA{D_EsDyD}@OcAq@aAeAyDiCg@cAw@cA_AEqAO{HsF{Bs@}CcAeAeB_BqAqB|DhBlBhC|OiKfMsImJmVr`@yBiC}MjTfl@fp@wK`R_FcFOyAyBcAmD{HeCOkBq@wDqEoBJ{DwEoAcA[QWdEEl@mF`}@uw@aHkb@l~IwlBaPh@~s@jAlbBd@CNEPYROb@CTF^Nh@@z@c@d@Id@Ib@At@Cx@G^BXANIXMZOn@Lj@Bv@UjAcAv@q@l@g@x@S~@Bd@EvM|`@ma@vVlBdGkUlMcEwLc`@n[xE`OQ\\bMj`@pMjDzS|p@uGtDzHrWe[rQsBmGwSjK}Yzf@oVvqAkUeBsCtq@gAbVc@AcJk@s@xOeMwEXwDmHiJ_NiG`CmKwIaJmFpJ}JuRl@mLyBiAiDsAaExIeCeBaPzNvEjE`JvEbIjNpCfCCXw@`UeQ}By@Mh@sKqO}A`AcQuJ{@HgD}JcAkDc@h@mImJaAuPgB_@jHqYmCLeCuWeCaLq@eKsG}I\\a@F@iCHeLl@_AfAoEYkHMwDsQqRqBuAo@]iBRoDjAeGrBoBrBm@nE_Jnv@ABOPuTdXePzg@sLxP_JlHoA|FaCxCOIw@_AeAqAQQIMKK[_@WYIKc@e@SUUUGIe@c@GGGGQQIG[[UQMIKIGEECECGCKEECMEEAKCG?GAQ?G?E@E?MBOBMDOFOFi@TMFMDKD]NUHSFSHKBSDI@SDK@Q@K@_@B_@BM@E@G?UBSBUDQDKBK@SHODUHEBSH[NOH_@Ta@TMJQHOJWNYPIFGDEDIHC@CBGHGFKNEHGHQ^KPCFa@t@~EjEtJ|GjGxKo@nA}LfVe@nYnCvGj@hFaA`F}@d@E`B~Lp^wNp\\|ZtDpRac@~KsPfAqXhAm@`@E^@ZT^d@^l@Xh@f@j@lEdC`AZh@F`@Cr@W^[`@g@^_@r@_@b@Mp@Bv@?|APnBRbBJ`AK|ABhBQfAQdA_@t@Wt@Qr@?t@Gn@Af@Md@H|@P\\Rf@TZh@f@t@^z@v@zBd@lA^jA`@lAn@bB\\nAL^XbA^~@Tp@Rh@Jz@Dp@Tl@Vb@f@RX\\T^Pl@?vBHt@Vp@`@Z`@Ld@?x@Ln@Zn@p@j@h@b@j@r@d@x@f@l@^bB`@n@FtABz@H`AT`Ad@j@^p@p@r@v@z@fAd@v@f@z@l@l@n@j@Vh@\\hAp@jAh@z@r@v@d@b@p@Z`Ah@dA\\vAd@f@Xj@Rf@f@vAdAbAx@fA~@l@`@j@Tt@PtAl@nAbAv@n@r@p@`@l@fAfBfAlBv@z@bAz@bAj@t@^f@^t@~@b@|@r@pAf@bAp@lAtAdBr@p@~@x@|@d@l@Tt@?dAM|@Q`@?f@Bf@Lx@Pr@D|@Ex@U^W`@Qz@Ch@Dp@Nt@RvAj@zAh@zA^jALlACt@ItAq@j@m@T[rAyAjAiAv@_@dAUdBEp@Ml@OvBk@n@C^Fr@`@hBlApB~AnBzAbAx@l@Zz@b@zBbApFzBbAVlA`@dAT`ATbATfAThDX`ALhAx@d@f@n@Nv@NpAPfA?jASx@Ur@Sr@A|@IbGFv@Dp@Xj@l@`@p@^d@b@h@l@b@^Tl@bAl@hAv@xBl@`Bx@|B`@nAd@fAd@rAV^^j@`@d@n@t@f@b@l@d@fA~@v@|@fAn@l@NrAChA?hAP|@Z`AZtAp@~@f@l@^l@j@\\n@Xz@VhADlAFbAE~@@p@Rr@b@x@n@v@fAjBfApB^bA|@dBPn@\\h@j@d@`@x@l@zAz@pCp@vA`@pA\\pAHbADhBZp@b@vARvAdBvBhAfA|BlBlAhAhAfBhArBvAtA|@p@fBlAdBh@`ADr@EhBc@nAFpCLvBIf@CzDYhBChBQnBBz@[vBqA`@QlGH?bAFl@^zAd@z@`@f@l@Zn@Ll@CRVHXDhBv@~A`AzArAzAnAjAl@Vb@Lx@LbA_@d@Wx@gAp@cA\\WZGl@?n@Td@b@^p@b@rA\\x@XZdAb@r@RX^lAxBXR`@^hABr@BbB^nA^`A@fAIz@k@h@@j@`@f@XXDf@E|@g@j@?`@ZnAbBr@HnATd@Lz@l@ZFh@Cd@YZm@x@i@PmA`@q@f@E`B]r@i@p@Uv@EbBKfAe@jAU`A[nAu@HgAXsA`@uAR[`@LVPx@r@n@^x@QbA?r@Jb@Zh@p@ZP|AN`BTlAGbCeApAu@n@C\\JVVl@El@CtB@fBm@lCqBx@qAf@e@z@yA\\_@\\Ir@BpBL`@k@R_Ax@wAp@[d@CvAKzAi@|AgAx@[h@CtALrAZzAEbBc@xBiAtA_AXoA^iAv@cCDw@G}@Ys@Ym@Fu@z@Up@J|@NhAOr@]r@w@zAiAlB_Aj@c@d@uAj@_A`AaAt@qATcADMfAm@x@y@dBqDd@aAVI|BLr@If@a@Za@l@DlAp@rBLf@^v@bAdARdA[v@q@d@b@i@zBChAT~@r@nAh@`Bz@fCdBtBn@r@ZhCZdAXxBTnAZlAn@P\\a@p@kB\\}@Xa@h@Kt@Zf@Ab@MZi@VGXVJf@?p@Lb@l@b@z@RXZx@pAnElC~@r@|@~Ap@lAFbARl@`@l@tBIx@?z@b@h@b@vBrCp@h@fA\\j@?t@ZjA`Bf@f@h@HlCL~@bAh@l@f@ZhAj@r@Rn@L^?b@JVHt@?bA[x@g@f@Ib@Pv@l@`@v@d@`DHtBRn@`Ap@f@n@RbARx@Xl@Xr@nBpAt@|@Xn@VxAH^lA~AVf@\\p@\\^v@^p@jAVl@\\p@^h@jA\\`Ap@b@fA@rCMj@?n@Mv@nAGfAIhAg@r@QdC_@x@Bv@Dr@^t@j@~@r@^x@vAd@d@^Lh@Dx@^b@t@R\\l@I|@e@pAm@v@u@~@Sp@Mh@?`@D\\XLfABv@[x@m@Zq@^MXHh@Z`@Pz@_@dAcAf@MZT?l@g@zDBrAV~Ad@fAhAv@~@j@^b@Hf@Ol@y@p@Y^WdBy@xAQr@`@TXFx@]n@[|@PNZT^Pb@d@Hb@?rA_@h@HNPHZdo@nx@d|BrtC|l@qm@v^e_@~vHe{HjJqJvIwP|Ra\\hOiUrRxKrKsAjYqArTW~Tl@vHhExEvEzNvAv\\bFhPw@dNiDbNnDdFvEjMl^hQj[hHzHhKY~KqFhHeLzCqCnB{C|RaGdJoElJiLdGaST}VHuJBBp@HnAUh@AlA@tA?l@IbAu@d@e@tAcAZChCD~DLbAVvA|@~@TlBPrAQpAIhB]tABtAPhA\\x@b@lAhAfB~Ar@f@j@TnALv@Tl@Pd@Z\\f@\\f@VHTI\\Kl@c@\\ClD@dCUzAEtALlADdCSdD{@|Ac@nAWnA]hB}@rAcAx@y@t@{@f@g@fA{@fC_B|@e@b@?^Rb@Td@P^H|@NzA^tAt@jBpB`Ap@`AZbBLfAFtAf@hAl@vC~@~Bp@jC\\fAHbAb@rAb@hAZv@F~ACv@I~@TvA?~@[n@Qz@GhBf@vAb@tAf@jCbAhBt@fARr@AfC_@nABv@Lz@CjAQ~@Ah@Rd@Xt@z@bAj@hBR`BL`AGzAa@|AkA`AiAr@mAl@kBj@_Ah@q@dAcA~@w@r@}@p@mAX_@tA_AhAu@x@[nAMfAQ`AQh@HfAf@nAp@z@L`AChAStAg@nBStBc@tBBnACnAMn@a@z@gAfA{A`Ak@hAa@~A]hBeAt@{@Zu@d@wBb@yBd@cBl@_Bz@o@dAq@`A[`AEl@Bv@b@v@bAz@zAj@t@z@h@hBtA~A~@jAl@|AfAhAz@Zp@\\jARdA`@|@Zl@zAj@jAb@tAp@fAp@hAh@`A\\jDl@~Bt@hBfAf@Fx@YTm@fAkBrAqCzAcC~AiBfAqA`Ai@hA[z@k@~@cAhAsAd@}@r@_@vA[|Ac@tAs@l@c@`Au@lA[zA[`ADhA@l@Iv@NrAQt@_@jBcBnB{Br@cAnAqAv@qAh@_Ar@w@n@m@r@u@fAc@r@I`CLnCPvBTpBFhCQnBUnC_@lBi@`Cy@vAq@hAq@dAq@n@Uj@B`@Xb@x@`@~Aj@`At@`@z@`@lA\\z@^~AhAx@ZdATt@Cr@Mt@[|@y@dAeAzAqBr@]~@a@~@c@n@k@\\a@Xg@ZY`@Iz@B`BVxAp@z@X`BTbCLfADzAf@hBHpBEvBUdCQhCCvDHt@Il@?`@a@^gAXm@DkAJcANwAJuAOgAM{ABq@J]TOl@UvAc@hAc@`Ae@~@y@`BiBj@kAf@mAd@kBZ{@\\Uh@Er@KhB_A|GyDh@MjAFjA?z@Gp@Q\\e@^_AdAaC`AaCbA}AfAgAp@q@r@c@~@e@vAqBfAcBzAuBbAkBd@gAXi@n@gA`AiCHc@Am@AuAHq@f@yAHe@Kg@a@k@q@_@rdBg@heU_HvBADrAv@~Ax@z@TbBnAlA\\tAUdBf@bBFfD`@~CAj@iApD?|@n@bCGxDa@bA[|@WpA{@xCQp@SbDBtATfDJH@^FjAXXf@pBAzAXl@n@r@|A`BL@|@x@^`@x@tAz@fAv@|@b@p@d@hBRn@F|A_@`Be@fA{@fDS|AE|ADpALbA`At@nAd@jC`AbCR`B@|BSlANZw@v@oCZ}@b@QBIBIDMRc@FMPYJMFMJMDKVUFEHIHEJETGPEHETe@HMNSJOBEFGRg@Da@LYDQ?M?c@AI?M@MCg@?KBm@@K@KBK?MFW?KBQ@OB]?W?M@K@MBID[?e@AO?KBY?I@Y?K@MFi@DYDM?K?oABq@Fc@BKDYDQ@KF_@?K@u@@k@PuAJYDMBIFKFKDIBM?M?K?K?YDa@@M?UBKBM?K@IAM@WBKBMBM?K?g@A[?MAO@]@[?WAO?YDWNIP[RWn@aAr@cATc@LQBIl@o@HGFGJEFGHMRSXSj@UHEFETMJCLCHAHAF?H?L?H?P?H@HAH?\\CHAFEHCHEFEHILITQTMHIHEDIFWFIFKJGTEJ@VBH@H@H?H?JETMZ[JGHG`@GD?J?HCVCHEPILCHGHAFEHGFKDKL[JYPYHKRSHGJGLEHCVMTOVQHIPUJWBM@IFQBK@W@I@M@M?M?MBWB]@MB]?i@AMAMQu@G]C]?M?c@B[BYJWFOBIDIHKDKZ]PQJITMHGPULYRWFIHIRMHCF?j@?RCPCHGPMHEHAHC\\IHCHIHMBIBu@Fa@FOPWFIHEPSTOJI\\SRQJKJOBEDY@WAm@?M@O@MDc@FYN]Le@DM@MDK@MDY?K?M?K?m@@]BM@KHi@@K@SBMLKDCFMJYHGHGLCJAd@EHCH?HCHAL@LD^NRHHBH@HAHEFGHMFKBY@Y@IHYDMZe@DKJWJWLq@JYFKPSPOHEHI^e@FIFIFKN[LWDIFOBM@K?[AY?I@WDKJIFAHAH?JAR?^DHBLHJJRJFFRDH?HAJAHAFCTCH?J@JAHAJCHERQHKDIDM@I@Y@I@O@MBIHWHKHC\\Cb@HHBRDH@H@H?PAb@QJCJAHAVCTCZCF?JBDDRZBHFNDNFPHJFHHFPJHBH@J?HAFCHGHML]BM@MDULa@FKJKHEHCL?F?HBRJHLJTNtADVNb@HJHHTP@@JDP@HEFGHMFKBKBIHQ@KPg@JWZa@HIJOFMLYL[BM@KBIN{@JWFINWFGHI`@]HIFERQHETQTUXYJKFILOHMFMFMLa@F[?ID[Ds@?YGs@CKGMGMEKEKCM?KAM?KFWDMPWDIH[@KBK@OBMLw@DIFYDY@MB[?i@Cm@?ICe@@KC[AK?M?M?MDWBIHOLOHOTk@NUFKLMLUHOHMDKHKHKFIHIJKFIHI`@UVQHKHEJIHGJEHEHCFCHAHCTMJC\\SFALENEj@QHEHEJGRMTUFMJIHMLKHKXe@FKFITWRUZYh@c@HEFEJEJMBGNe@DYDMDKFKLEJCJCHGFIJYLm@BOFYBMJ[Pq@Pk@FOBKH[DIXcAR}@DWJu@BOD[FYBMH_@BMBODKLo@BODOBKLg@F[DO@ITcAD_@BO@MHg@F[BODu@BUBMDOFYBIDKJYBKJMBIDKRYV]FMNYNa@PYDKFKDKJW@M?KAMGIIMMUCKCK?MDWBOBKDW@IBOFWDOLWDOBMHYDWDY?KHi@?KD[@K?WEUEKSUIMEICY@[BKNi@DKBMFKLUHKRUHIPMJEFGTWNWHIHI^WHKHIHGHIPMRSHMN[DKTe@JUDMBKBKFY@I@[@i@Ce@CI?KCMEKEa@AK@q@@MBIDKXMHKLYHMHEHIFCPMJMHOHSTg@JKHMT_@BKL[DOBIF]DWFm@@MBKBMBKDKBKDKNYFK\\k@DKFKDM@KJ_@HWLc@FKFIFAJDDBJDLGBEFKDIBKBMBIDKDMDa@@w@@[BMNi@@KDY@KHe@DYBQ?y@@MAK@M?M@KBy@?YDeA@M@MB[@IBWHg@BUDMDMPg@HYBKJWHGHAJ?LBH@L?PMRSN[BKDOBY@WAYAIEMIKCM?KJWFMBMHW@KD[?MAMAMCKCIIKUUWSOQIKEMGKCKEICKEOCKAK?KBi@?I@Q@U@KRu@DWLg@DODM@IFYBY@WCWEOGKCKGKQa@CKCKCKAU@O?O?K@U?K?M?K?K?K?YAO?[AM?[?I?k@C[CKCKKWIKGIIIII]c@GKIKGISWSWKOSg@IWKUM[SUS]KKIOIKIKUSQOMEIEGCKCGAUESAGEGKAI@KBKLc@Fc@@M@MBKJe@DWD_@Bg@?K@K?e@?M?MCi@C]?M?K?o@?K?KDo@@K?M@KAKCMAK?KAW?KAIAIIg@CKCKEKEMCMEKEMEKAKMWSo@CKGWGk@Gg@CQAOGc@EQAOMcAIeACOAOAM?{@B]@I?KF[BWB]?GB]BU@MDk@DiAF{@?M@KB[Dk@DU@M@IJ{@?KDYDs@Bc@@K@M?K@K@MDkA?m@AW?ICg@AKCi@AOGsAAO?OEOI[AKQk@Ki@IYCKEMAKEKAIIQMWEIEKKWCK?YDWFULYJWDKDM@KFML[ZeAN]DIJK\\_@RWP[FOPYBI@WAMGMUMKAIAK?SBI?ICIAQEKEGKQWIMQSGEKEICe@GIAIAS?I@S?KAIAa@EK?I?SEICKEa@OIEGCICKAMCK?GAI?I?S?GAK?KAG@S?I?U?I@I?UDWFUHc@FG@I@K@I?G@I?I@G@IEIIGGI?IBK@I?KCIAQDKDIFIDKLGJKDKJIBIB[LKBWDI?_@?GAICIICEGOAOA[?M?YAIEKIEICI?]IKCGEGKCM@M@MDKRMJELIHCHGPKROFKFIBKD[?KAKAKCKGMQSIIQWGOGKCIQe@EMEKGKUYGKKIGKSS_@c@]e@OYGKGMICe@K_@MECMOGIIKGKSUOWQ[Yg@MYEKOa@IMGOEIEMIKOm@EME]Gc@?M@M@K@YAICEBYDOBKDOb@q@HILMl@e@JId@YHKROJGJIr@s@JMJKHGLQHK\\a@v@u@HOJGFKRWHKHMNYLYDOD[B_AAm@CKESEIIIWOMGKIIIKOIQCKQWMKECGGMIIKMQKQEKG]GSEKGMCKIIIIGEKAKIWIMG[M_@MGAQAGEQEa@MICWKUMKIGEIIIMEMAMCOAOE]Sq@I_@EWAOCa@O_@IMGIKISMIGKEKKEQKg@G]Ia@C_@CIG_@AQCIAMEQCWCg@?M@K@[DIBQDK@O@W?K@K?MC_@?OEy@EWE[EYEMCKAW?Y@MBIHIREJAJ?H@PBL@J@T?J@L@H@VDZLZPRPTLXD`@BH?FAHMBM@M@WAO?c@@O?[@K?I?KBK@Q@I@KN[`@w@\\a@LOHIJOHOZg@P]DKJIXe@FMDKDKL]HYBY@K?KCOCMAMCMKQEMAIEOCW?KBKDKFIHIDKHKLYBMDM@KBOBg@?I?g@CO?IEc@A[@YBKHQHKHMLOFMJMJMFGV]JIHMHSNq@Bc@BKBKFKFIHINMVCL?t@GHALAD@J?L@PBH?LEj@e@JGJGRGH?jAAJ?LCHAXQTOXQHIHEHEZIn@I^MFERSBKFc@DM@MFMDMHMTYNOFIHIFIHIJGFEHAHAN@H@HHHJDJFJHHJFFBNBH@LCPMHKDKHKd@}@DKHOFQFKFKBKJMDIJOFIFOJOV_@LKTULIZQVOLE^SHC`@Kl@QJGJIDCH[BMDQ@MNi@DOHYDKHKFEJEVEHCHEJGRQJGHCLAL?HBH?JDXJH@RHH@F@H?HAHIFIBMDKFKVOLAHAH@^FJ?\\Bb@?RCX?TCLKHKHGPOJKJIJGHILKFG`@[HERIH?HJDLDZ?N?H@\\BHBJJLL@JCJKJMVg@FMJMLYFITMJCJ?LDF@JHLLFJJFHDH?J?FOLg@JWHWFQNYLEJAL?H@LDZXPHFJF?HEFIN]Je@FOR_@DMBK?Q?Q?MAIAO@O@WFYHOFGJMHGT[HMNYDK?K?MAMCg@Ia@?M@K@KBIHQFIJGTGLCHCPCVEHG\\GPELGRMHIHCLELEJEJGROJIHIJGHITQHEFCLCLG`@Md@QHGHOHi@F_@FKLKZMH?HALCH?`@EZG^MVAH@TAHAHAHAHAH?J@HBZHHBRBTBb@JHBFBTHAJKf@AHAL@NBRHVTHJCHEVYJELIHCJEHCd@SHAFEHEJCFEVKXOXMh@YLGNKLEHGJIRQPYLMXe@FMFOFYHWDO`@q@PY`@q@RUFIPWRKXOJILEFINIJCHGROb@M^Kd@WNEZOHCLKLGNKLGb@[PSRYBKJOBKFKVm@JSDIFKPe@DO@M@OAY?Q@KDKHKHKJINIJCHEHCXGb@IXEF?J?RCT?HAJ?ZC^?L@H?T@L?FGLYFKDKFKLONW?IIMGGKEIKMEGGEGGO@O?GBIBOHOPWJKHKZIZKHGFI@KEMIOQYCKGMEOAKEUCKHYJYHMTs@FMFOFKJKRQHGDKJQHURiAB[@MDYHQN[HMJOPYLKJKFKVY`@]JKHMLWFOLYL]HYJWH[HYBM?KIWAMKWGKKIKIIGGCUKUUGKGOAKBO@W@K?YBU@QD_@Bi@BO@K@ML}@RiA@MHc@BK@KN[FMHGLMHIHMHODKTc@FMFIJGNMJG`@OLEHEHIFOBMFg@Bo@?I@W?MDi@B]Fe@FYFSDKBIHSJONOLOPOHIHEFGNKLIHIHKFKDKHUDKBKHODWFSDODM@KN]TUJG`A[LCFEVEJCFE?KIKGEGMCM?OBOBILGVMXGn@KHKJIDMDO@KNs@L]JMFGLEJEL?PBJBHNJ\\FZ?JLl@D^HPTPH@H?JARCJ?HAJCHKLO?MCQEOCKIQEMGOCMGSKYSq@M{@COOg@ESCOCa@?Y@M?O?M@ILQJWPQPYHKHIVYHOHIDMDIFO@IJMHGLCJCHC@WAME]?c@Aa@CSC[?S@e@Dk@Ho@@O@m@?e@DgA?K@_@?O@K@KBQBQF]@Q@KHc@B]@Y@O@M@c@?Q@Q@o@Am@AO?OGy@CWAYEY?OImAAKAYAM?o@B]FQHKHIFKLGHIJGJGHGb@UJEJC\\AXB`@FL@T?HAHCLGLG^IHEHANIJGRQJGPQHMTWFKJOVk@N_@FIDONa@`@uAFQFMXs@FW@I?QCMQe@[m@CKCKAIAM@QFg@VeADKPm@BKL_@DO\\g@HKVa@BKJMHOFMXk@DMHIHMDKH[?O?U?KAKCMAOCMAO?MDM@MHKFGXMLKFIPGPOHELGJIFGJIVSHKHGJMHIHMLOBKFMBK?MCYCSCKEKAO?K?O?EFORU^WHAJGHCJEFEJCXIHAHAJ@P?TCJEHGH[DKRWPEHILGHGHELEHELC~@ORIJIHETILGTIPCREJCPAREHAHAJAp@DH?RB\\AZGhAUhBYtBUhA]b@URYRWTMZIPMTEJ?D?NDLDVJTNr@v@HLHJJPFRNXBHDJDJFJJLHFLFJHF@J?JIHEHIHO@MAMCMWe@EKCKBSBKHGFAHCFAJ@F?TAHALAt@QHAJCJAH?PAJ?HCf@EL?L@T?V@H?N@L@H?H@H@NFHDHDNDJFJ@JDJ@JBN@HBJBR?HCNEJIROLGFILEHGHCTOHGFK?SA]Cc@KkBCc@E_@?KEg@CWC]CSGSG_@CMEMEMEOGOMm@Km@UaAAM?K?M@QDQPa@JOJYFKJUDQL]BIFOH]JQDQDOFWHOBMNg@FMFQTk@HWBKFKDKDQH_@H]He@D]DOP}@BYBK@UDU@]@K?MDw@AI?u@Ec@AIC]AIC_@AQCe@C[Aa@CS?u@@K?W@OB]BOF[DSJq@DKF[Na@RUTeCxaAisMA?y@m@[wA@wAg@y@g@J[fAWlBMjBOjAYbBqAv@uAMo@}@u@_@i@e@s@THbADlADv@TlBGvBYrA^x@h@jAWx@y@VyAJkAZWbAAfAu@j@]j@i@XeBAg@AG~@FhAKtAMpBu@j@YfBe@jAaAh@wAVq@c@uAOw@v@k@bAq@RaA?cB@mBAe@UFqBb@aBh@iASgBI_COmAgAaBu@kBaA_Cy@i@cAHu@j@_AlAuAjAqBvAaBZaBe@mBk@q@LSr@Qz@i@j@iAzAm@fBc@hB]lAs@p@cAl@cANiBLsA@}AFuARmAd@oAv@gAf@_ATq@h@MtAP~ANdBKnA]bCG`C[lE@bA_@dAo@Ru@IgAk@}AmBmA{@mBs@oA_@oBe@iB]mANgAl@g@n@e@jB[dBSf@y@j@SF}@NcAl@u@jAa@`Bg@Pg@q@LqA`@{APqBEyBm@{AaAMu@JyARs@NgCdAwBt@{At@qAXeA?oADeA\\w@t@o@v@{@nA}Ap@oAlAs@x@eB`BaBZgBVyAh@mAb@{@RoAJkBl@_Bn@{Ap@yBdAkBhAgBr@cACkBGcBIoBWwBS}@_@q@e@k@wAe@mAcA{A{@g@aATc@`@k@fAm@xA]tAc@fAqAhAuAPsADsBEwANiAJiAn@k@t@_AvAa@dCAzDHvBHdBP~BCj@QxAyAfAeA\\s@]w@g@g@g@wAm@cAe@u@i@}@SgA?o@Sa@Go@GcAAq@CeA?k@Ms@_@GC]k@i@o@u@}Ai@aBi@[m@e@iAPg@h@w@dA}@x@sA\\mBVyAKcAk@u@cBMsBUsBMqCs@_Cm@wAm@a@mA_@w@CaBCq@cA}@qBk@y@oAe@q@Xa@j@{@`@wA~@qAn@uAIU]?kALYb@cA?{@ScAa@}@g@sAMeAMg@s@o@{Ae@gAAyAVcABcCJwAE_Ae@{AEsBEo@E{AUsB[uBKgCCgBXy@n@}@b@gA^}A`@qBXaBZiBf@}Av@qCnBiB~@gCh@cA`@QV@f@Ll@?x@Mx@c@|Ac@x@aAn@m@Mg@Ig@Ne@j@k@fAWj@c@|Au@|@s@t@aAl@aBj@o@Lu@Ay@Km@Uw@@y@Gs@Gm@EeBIuAQGe@E{@O[k@_@o@?e@\\D|@Yt@Uj@YVg@Nm@Bs@Io@Ku@Dk@Za@Po@Be@Ke@I{@YaA?k@^KNgAhAq@|@g@h@wAx@eATw@_@mAe@c@IeA^}AV_AJiBRwA^oAr@aA`@YJy@Pu@QmAe@y@Ss@BwAZw@d@g@^a@\\s@P}@?m@N]x@Cl@GrAEbBUn@a@r@kBVgADm@Ic@QSq@Wu@g@]u@E{@b@m@r@o@n@[l@a@d@uBEyBKmAUcAYaA}@[e@g@?cAf@cAh@u@P[?c@L_ANYGIi@JgAH_AHu@UiAYs@Y]cAm@s@_@_AB_@Ra@d@[RW@YULy@Dk@Gi@Ui@y@u@sAWiAAsAPeARy@Sk@e@_@eAMo@a@Ws@To@VoAX}ARkBWuAe@qBoAyBaAcAa@w@WeAGgAOyAw@aBy@o@]y@QgAT{ARoBJkB^qA~Ai@r@_APkADmA`@o@XiAGcBwAqAeAoAoAyAaAiBUqBKmB?yBHmAd@aAjAg@dB]z@wAl@sA@wAU}AK}AI_CHgB^gAf@uA`@mA^eBNqAIi@UqAOoA^}Br@uA`AkAz@_AjAkA`BoAlAaB`AeA~@aA|BGrAAlCK~@_@~@o@^q@^Md@i@t@i@~@[x@c@~@e@b@s@Rs@UaAkAcAsAo@{@iAWkBDgAVkBOwB{@kAk@kAEkANeCFmAKuCq@sAWqB{@uBq@sBw@oB]mB]_Bc@cAu@}@iAaAkA{@i@uB}@qAi@eBaAu@aAaAcB{@eBsBsCkBqAuAsAqBkAw@u@}AsBoAeBgAmB[iAUoAg@uAe@qCGoAUsDk@yDm@kEg@sCaBmFe@sAoAsAc@w@Y{@gAiBcAeAkAaAw@Y_Bw@sBy@cAs@aBo@yBPoB`AwAj@yB|AaAz@_AnAwCbEsAbBqAjAk@dFoOtFwBgCs@ReAJyB@}@OQGm@a@sAm@cDaFsA}CyAkCqAiC{AcD}@kDUoBa@qDw@sEc@sBSyATsCBkBCiBUaAqA}BaAmDcAmCmAsCcA{Cm@eBe@_AgxCL{wAFodFDe^@SwwMm@Bo@XiHtBeCDqDkAaHoDcM_N_BqAkCy@wEu@eFBoFZsDl@{IvBiGYqDw@eEkBiCuCcFuKgCyDs@a@o@UYLkABwB|@]\\wAxAsF~C{DxAeB^cDz@cEfBuCf@{GEmCMyF`@cDAkC[}EeCsC}C_VcMavEBeXhkO?xo@kzJcpBuuCqi@swAd~MfMzExEy]nz@hPmGnk@dA|Cy@PcBAkDoBaBcBoDg@aCy@cA\\m@QyAn@{BM}EmMgBu@qDaAcEOoFBiBd@]bDoHbBu@d@a@HgB`QuBXaFYeE}BeCm@{Di@cB_BeJeMuAy@sAE}Af@sA`Bi@l@iCCyBm@YaBKmB_AsB{@kBoAk@aCCiJLiEKgAkBk@gFPgF?mC]{@a@i@cRpm@uQwKaMmF{CmKig@mc@}HsCs]ck@xVgWmFcBoDeJeFlBwHrCk\\{C{A~McZ}FeBxOzIvDaOnn@GRc]{`@UDgAtFor@_ZvG}XrGuXzNeHGUkFN{NbFmPh@{EVeBnD[i@eAiB{@kCwIaIO{CLWuI{IwH`@aA~HiMaC}\\hM{KtEaUwEa@IgIrj@b@J~UpFe@zIbJsAzAuA`H`PcI|H_N_A_BnZpK`Ak@nIb@F`jAvKgF~aA_Eo@cCkD_Hm@aIaK}I\\SUwLiJ}OkQe@?uJO"
  },
  "postcode": 3737
}