{
  "state": "ACT",
  "suburb": "Hackett",
  "gender": {
    "Male": 1381,
    "Female": 1533
  },
  "age": {
    "0 - 4 years": 224,
    "5 - 14 years": 337,
    "15 - 19 years": 138,
    "20 - 24 years": 164,
    "25 - 34 years": 369,
    "35 - 44 years": 477,
    "45 - 54 years": 407,
    "55 - 64 years": 305,
    "65 - 74 years": 242,
    "75 - 84 years": 200,
    "85 years and over": 52
  },
  "school_completed": {
    "Year 12 or equivalent": 1739,
    "Year 11 or equivalent": 81,
    "Year 10 or equivalent": 275,
    "Year 9 or equivalent": 71,
    "Year 8 or below": 95,
    "Did not go to school": 11
  },
  "marital_status": {
    "Married": 1105,
    "Separated": 60,
    "Divorced": 187,
    "Widowed": 134,
    "Never Married": 871
  },
  "country_of_birth": {
    "Australia": 2217,
    "Bosnia and Herzegovina": 6,
    "Cambodia": 0,
    "Canada": 20,
    "China": 31,
    "Croatia": 3,
    "Egypt": 0,
    "Fiji": 6,
    "Germany": 29,
    "Greece": 29,
    "Hong Kong": 6,
    "India": 15,
    "Indonesia": 15,
    "Iraq": 0,
    "Ireland": 5,
    "Italy": 19,
    "South Korea": 7,
    "Lebanon": 0,
    "Malaysia": 9,
    "Malta": 0,
    "Netherlands": 10,
    "New Zealand": 44,
    "Philippines": 6,
    "Poland": 9,
    "Singapore": 3,
    "South Africa": 12,
    "South Eastern Europe": 0,
    "Sri Lanka": 7,
    "Thailand": 6,
    "Turkey": 0,
    "United Kingdom": 136,
    "United States of America": 30,
    "Vietnam": 10,
    "Elsewhere": 145
  },
  "languages_spoken": {
    "English": 2451,
    "Arabic": 0,
    "Assyrian": 0,
    "Australian Indigenous Languages": 7,
    "Cantonese": 4,
    "Mandarin": 24,
    "Other Chinese": 3,
    "Croatian": 7,
    "Dutch": 6,
    "French": 28,
    "German": 44,
    "Greek": 54,
    "Hungarian": 3,
    "Bengali": 9,
    "Hindi": 0,
    "Punjabi": 0,
    "Sinhalese": 3,
    "Urdu": 3,
    "Other Indo Aryan": 6,
    "Dari": 0,
    "Persian": 13,
    "Other Iranic": 0,
    "Italian": 30,
    "Japanese": 3,
    "Khmer": 0,
    "Korean": 9,
    "Macedonian": 0,
    "Maltese": 0,
    "Polish": 7,
    "Portuguese": 0,
    "Russian": 4,
    "Samoan": 0,
    "Serbian": 0,
    "Filipino": 3,
    "Indonesian": 8,
    "Tagalog": 3,
    "Other Southeast Asian": 6,
    "Spanish": 34,
    "Tamil": 3,
    "Thai": 3,
    "Turkish": 0,
    "Vietnamese": 13,
    "Other": 59
  },
  "religion": {
    "Buddhism": 58,
    "Anglican": 326,
    "Assyrian Apostolic": 0,
    "Baptist": 36,
    "Brethren": 3,
    "Catholic": 627,
    "Churches of Christ": 3,
    "Eastern Orthodox": 84,
    "Jehovahs Witnesses": 10,
    "Latter day Saints": 0,
    "Lutheran": 36,
    "Oriental Orthodox": 3,
    "Other Protestant": 0,
    "Pentecostal": 8,
    "Presbyterian and Reformed": 65,
    "Salvation Army": 0,
    "Seventh day Adventist": 3,
    "Uniting Church": 124,
    "Other Christian": 52,
    "Hinduism": 18,
    "Islam": 37,
    "Judaism": 11,
    "Australian Aboriginal Traditional Religions": 3,
    "Other religious groups": 61,
    "No Religion": 1151
  },
  "weekly_personal_income": {
    "No Income": 118,
    "$1 - $199": 140,
    "$200 - $299": 167,
    "$300 - $399": 152,
    "$400 - $599": 207,
    "$600 - $799": 209,
    "$800 - $999": 203,
    "$1000 - $1249": 222,
    "$1250 - $1499": 192,
    "$1500 - $1999": 340,
    "$2000 or more": 339
  },
  "number_of_children": {
    "No children": 470,
    "One child": 169,
    "Two children": 315,
    "Three children": 178,
    "Four children": 59,
    "Five children": 18,
    "Six or more children": 12
  },
  "weekly_household_income": {
    "$1 - $199": 8,
    "$200 - $299": 28,
    "$300 - $399": 58,
    "$400 - $599": 58,
    "$600 - $799": 63,
    "$800 - $999": 70,
    "$1000 - $1249": 74,
    "$1250 - $1499": 83,
    "$1500 - $1999": 132,
    "$2000 - $2499": 79,
    "$2500 - $2999": 116,
    "$3000 - $3499": 94,
    "$3500 - $3999": 43,
    "4000 or more": 126
  },
  "vehicles_per_house": {
    "No motor vehicles": 99,
    "One motor vehicle": 471,
    "Two motor vehicles": 417,
    "Three motor vehicles": 105,
    "Four or more motor vehicles": 38
  },
  "monthly_mortgage_repayment": {
    "$0 - $299": 19,
    "$300 - $449": 9,
    "$450 - $599": 3,
    "$600 - $799": 12,
    "$800 - $999": 18,
    "$1000 - $1399": 43,
    "$1400 - $1799": 46,
    "$1800 - $2399": 78,
    "$2400 - $2999": 61,
    "$3000 - $3999": 56,
    "$4000 and over": 37
  },
  "weekly_rent": {
    "$0 - $74": 20,
    "$75 - $99": 21,
    "$100 - $149": 24,
    "$150 - $199": 12,
    "$200 - $224": 11,
    "$225 - $274": 29,
    "$275 - $349": 44,
    "$350 - $449": 62,
    "$450 - $549": 57,
    "$550 - $649": 12,
    "$650 and over": 3
  },
  "internet_type": {
    "None": 189,
    "Broadband": 854,
    "Dial up": 47,
    "Other": 41
  },
  "level_of_education": {
    "Postgraduate Degree": 367,
    "Graduate Diploma and Graduate Certificate": 144,
    "Bachelor Degree": 675,
    "Advanced Diploma and Diploma": 156,
    "Other Certificate": 37,
    "Certificate III and IV": 168,
    "Certificate I and II": 14
  },
  "qualifications": {
    "Natural and Physical Sciences": 168,
    "Information Technology": 67,
    "Engineering and Related Technologies": 136,
    "Architecture and Building": 78,
    "Agriculture Environmental and Related Studies": 51,
    "Health": 101,
    "Education": 138,
    "Management and Commerce": 224,
    "Society and Culture": 469,
    "Creative Arts": 111,
    "Food Hospitality and Personal Services": 23,
    "Mixed Field Programmes": 0
  },
  "industry_of_employment": {
    "Agriculture forestry and fishing": 3,
    "Mining": 0,
    "Manufacturing": 26,
    "Electricity gas water and waste services": 9,
    "Construction": 62,
    "Wholesale trade": 12,
    "Retail trade": 83,
    "Accommodation and food services": 70,
    "Transport postal and warehousing": 25,
    "Information media and telecommunications": 53,
    "Financial and insurance services": 22,
    "Rental hiring and real estate services": 15,
    "Professional scientific and technical services": 177,
    "Administrative and support services": 38,
    "Public administration and safety": 513,
    "Education and training": 197,
    "Health care and social assistance": 108,
    "Arts and recreation services": 39
  },
  "occupation": {
    "Manager": 258,
    "Professional": 627,
    "Technician / Trade": 116,
    "Community / Personal Service": 101,
    "Clerical / Administrative": 229,
    "Sales": 68,
    "Machinery Operator / Driver": 27,
    "Labourer": 59
  },
  "travel_to_work": {
    "Train": 0,
    "Bus": 99,
    "Ferry": 0,
    "Tram": 0,
    "Taxi": 3,
    "Car as driver": 830,
    "Car as passenger": 88,
    "Truck": 12,
    "Motorbike scooter": 23,
    "Bicycle": 132,
    "Other": 4,
    "Walked only": 29,
    "Train and Bus": 0,
    "Train and Ferry": 0,
    "Train and Tram": 0,
    "Train and Car as driver": 0,
    "Train and Car as passenger": 0,
    "Train and Other": 0,
    "Bus and Ferry": 0,
    "Bus and Tram": 0,
    "Bus and Car as driver": 3,
    "Bus and Car as passenger": 6,
    "Bus and Other": 6,
    "Other two methods": 15,
    "Train and two other methods": 0,
    "Bus and two other methods excludes train": 0,
    "Other three methods": 3,
    "Worked at home": 62,
    "Did not go to work": 178
  },
  "spatial": {
    "pole": [
      -35.25023715443409,
      149.16289393535055
    ],
    "area": 195.4288444818779,
    "poly": "|abvEillm[rEhG|F|HdB~BjHvJHLNRT`@Rf@FJHPZfAv@`EzApHnGcBlEkAz@U~@a@`As@z@}@l@_A?ALW`EgIpDoHb@s@h@m@n@g@p@]v@Sz@Kp@Ar@DbDl@pB`@dAb@jK`FfHuC{EeSIa@Ki@Gi@k@iGCUE[G]EUOm@GWM[KYOYWe@OWMQMQOQSSMKSQQOSKOKUKUKUIQGQGUEa@IgC]QCYGWIWISIQISMQKOKSO][kJgJYWWO[SYOUKSIQGWGQEWGSCWCYAQAS?W?W@SBC?UBSB[HWF[J[LqG~CSJA?GBA@C@A?IDE@E@C@C@E@A?ODA?E@A@A?C@A?G@I@OBA?C?A@A?A?C?C@A?I@A?K?A?E@E?A?G?C?A?C?A?O???G?A?C?C?A?K?A?QAAAC?A?GAA?E?EAA?QC??KCA?CAC?AAC?AASEsDeAaAW??CAA?MEA?EAA?CAOCGAMCA?MACAG?A?CAA?A?C?CAE?GAC?GAC?A?KCA?E?AAKAA?SCBq@C?A?W@A@C?I@G?E@A?OBa@F{Dl@A?I@A?C@E@A?E@A?SFA?GBIBC@A?GBGBA?GBA@C@A?KDIFA?SJA@GDA@C@A@C@KHKHC@CBCBA@CBA?GHA?SR?@CBA@A@A@A@IJEDABCB??A@EFA@KN?@ABC@?@ABA@A@CDABABA@EH?@CB?@KTCDABAB?@GL_DtIABCDAB?@EHABCFA@INAB?@ABA@A@A@?@EFABuA~BrAhBJL`HjJ"
  },
  "postcode": 2602,
  "average_tax_return": {
    "taxable_income": 63318.37280168999,
    "gross_tax": 14653.889199894376,
    "medicare_levy": 870.2015315553208,
    "help_debt": 326.32711909162924,
    "gross_interest": 1623.6496963295485,
    "work_expenses": 1089.8708740427778,
    "donations": 333.1651967256403,
    "child_support": 44.46928967520465,
    "gross_rent": 3627.7776076049645
  }
}