{
  "state": "VIC",
  "suburb": "Tecoma",
  "gender": {
    "Male": 1041,
    "Female": 1047
  },
  "age": {
    "0 - 4 years": 148,
    "5 - 14 years": 280,
    "15 - 19 years": 158,
    "20 - 24 years": 138,
    "25 - 34 years": 201,
    "35 - 44 years": 329,
    "45 - 54 years": 364,
    "55 - 64 years": 272,
    "65 - 74 years": 111,
    "75 - 84 years": 72,
    "85 years and over": 15
  },
  "school_completed": {
    "Year 12 or equivalent": 874,
    "Year 11 or equivalent": 249,
    "Year 10 or equivalent": 257,
    "Year 9 or equivalent": 92,
    "Year 8 or below": 65,
    "Did not go to school": 3
  },
  "marital_status": {
    "Married": 748,
    "Separated": 50,
    "Divorced": 194,
    "Widowed": 72,
    "Never Married": 595
  },
  "country_of_birth": {
    "Australia": 1644,
    "Bosnia and Herzegovina": 0,
    "Cambodia": 0,
    "Canada": 8,
    "China": 7,
    "Croatia": 0,
    "Egypt": 3,
    "Fiji": 0,
    "Germany": 20,
    "Greece": 4,
    "Hong Kong": 3,
    "India": 4,
    "Indonesia": 0,
    "Iraq": 0,
    "Ireland": 6,
    "Italy": 3,
    "South Korea": 0,
    "Lebanon": 0,
    "Malaysia": 3,
    "Malta": 0,
    "Netherlands": 15,
    "New Zealand": 24,
    "Philippines": 3,
    "Poland": 0,
    "Singapore": 3,
    "South Africa": 13,
    "South Eastern Europe": 0,
    "Sri Lanka": 3,
    "Thailand": 0,
    "Turkey": 0,
    "United Kingdom": 152,
    "United States of America": 9,
    "Vietnam": 6,
    "Elsewhere": 31
  },
  "languages_spoken": {
    "English": 1885,
    "Arabic": 6,
    "Assyrian": 0,
    "Australian Indigenous Languages": 4,
    "Cantonese": 0,
    "Mandarin": 9,
    "Other Chinese": 0,
    "Croatian": 0,
    "Dutch": 11,
    "French": 0,
    "German": 15,
    "Greek": 8,
    "Hungarian": 7,
    "Bengali": 0,
    "Hindi": 0,
    "Punjabi": 0,
    "Sinhalese": 0,
    "Urdu": 0,
    "Other Indo Aryan": 0,
    "Dari": 0,
    "Persian": 0,
    "Other Iranic": 0,
    "Italian": 9,
    "Japanese": 0,
    "Khmer": 0,
    "Korean": 0,
    "Macedonian": 0,
    "Maltese": 0,
    "Polish": 0,
    "Portuguese": 0,
    "Russian": 6,
    "Samoan": 0,
    "Serbian": 0,
    "Filipino": 0,
    "Indonesian": 0,
    "Tagalog": 7,
    "Other Southeast Asian": 0,
    "Spanish": 3,
    "Tamil": 0,
    "Thai": 0,
    "Turkish": 0,
    "Vietnamese": 6,
    "Other": 10
  },
  "religion": {
    "Buddhism": 24,
    "Anglican": 231,
    "Assyrian Apostolic": 0,
    "Baptist": 30,
    "Brethren": 0,
    "Catholic": 333,
    "Churches of Christ": 9,
    "Eastern Orthodox": 10,
    "Jehovahs Witnesses": 13,
    "Latter day Saints": 6,
    "Lutheran": 14,
    "Oriental Orthodox": 0,
    "Other Protestant": 9,
    "Pentecostal": 18,
    "Presbyterian and Reformed": 51,
    "Salvation Army": 0,
    "Seventh day Adventist": 7,
    "Uniting Church": 105,
    "Other Christian": 44,
    "Hinduism": 0,
    "Islam": 3,
    "Judaism": 6,
    "Australian Aboriginal Traditional Religions": 0,
    "Other religious groups": 46,
    "No Religion": 906
  },
  "weekly_personal_income": {
    "No Income": 110,
    "$1 - $199": 161,
    "$200 - $299": 139,
    "$300 - $399": 147,
    "$400 - $599": 195,
    "$600 - $799": 200,
    "$800 - $999": 154,
    "$1000 - $1249": 143,
    "$1250 - $1499": 98,
    "$1500 - $1999": 120,
    "$2000 or more": 72
  },
  "number_of_children": {
    "No children": 263,
    "One child": 100,
    "Two children": 227,
    "Three children": 145,
    "Four children": 42,
    "Five children": 24,
    "Six or more children": 3
  },
  "weekly_household_income": {
    "$1 - $199": 6,
    "$200 - $299": 25,
    "$300 - $399": 54,
    "$400 - $599": 53,
    "$600 - $799": 69,
    "$800 - $999": 54,
    "$1000 - $1249": 53,
    "$1250 - $1499": 46,
    "$1500 - $1999": 111,
    "$2000 - $2499": 65,
    "$2500 - $2999": 71,
    "$3000 - $3499": 45,
    "$3500 - $3999": 13,
    "4000 or more": 9
  },
  "vehicles_per_house": {
    "No motor vehicles": 47,
    "One motor vehicle": 221,
    "Two motor vehicles": 317,
    "Three motor vehicles": 102,
    "Four or more motor vehicles": 47
  },
  "monthly_mortgage_repayment": {
    "$0 - $299": 18,
    "$300 - $449": 10,
    "$450 - $599": 12,
    "$600 - $799": 12,
    "$800 - $999": 28,
    "$1000 - $1399": 64,
    "$1400 - $1799": 77,
    "$1800 - $2399": 99,
    "$2400 - $2999": 34,
    "$3000 - $3999": 21,
    "$4000 and over": 9
  },
  "weekly_rent": {
    "$0 - $74": 9,
    "$75 - $99": 24,
    "$100 - $149": 3,
    "$150 - $199": 10,
    "$200 - $224": 9,
    "$225 - $274": 23,
    "$275 - $349": 24,
    "$350 - $449": 20,
    "$450 - $549": 0,
    "$550 - $649": 0,
    "$650 and over": 0
  },
  "internet_type": {
    "None": 113,
    "Broadband": 581,
    "Dial up": 29,
    "Other": 12
  },
  "level_of_education": {
    "Postgraduate Degree": 51,
    "Graduate Diploma and Graduate Certificate": 59,
    "Bachelor Degree": 244,
    "Advanced Diploma and Diploma": 181,
    "Other Certificate": 18,
    "Certificate III and IV": 291,
    "Certificate I and II": 15
  },
  "qualifications": {
    "Natural and Physical Sciences": 36,
    "Information Technology": 24,
    "Engineering and Related Technologies": 166,
    "Architecture and Building": 61,
    "Agriculture Environmental and Related Studies": 29,
    "Health": 87,
    "Education": 104,
    "Management and Commerce": 131,
    "Society and Culture": 127,
    "Creative Arts": 60,
    "Food Hospitality and Personal Services": 34,
    "Mixed Field Programmes": 0
  },
  "industry_of_employment": {
    "Agriculture forestry and fishing": 9,
    "Mining": 4,
    "Manufacturing": 114,
    "Electricity gas water and waste services": 9,
    "Construction": 106,
    "Wholesale trade": 64,
    "Retail trade": 126,
    "Accommodation and food services": 65,
    "Transport postal and warehousing": 28,
    "Information media and telecommunications": 29,
    "Financial and insurance services": 32,
    "Rental hiring and real estate services": 21,
    "Professional scientific and technical services": 75,
    "Administrative and support services": 44,
    "Public administration and safety": 44,
    "Education and training": 115,
    "Health care and social assistance": 147,
    "Arts and recreation services": 16
  },
  "occupation": {
    "Manager": 119,
    "Professional": 263,
    "Technician / Trade": 188,
    "Community / Personal Service": 122,
    "Clerical / Administrative": 175,
    "Sales": 89,
    "Machinery Operator / Driver": 57,
    "Labourer": 83
  },
  "travel_to_work": {
    "Train": 57,
    "Bus": 6,
    "Ferry": 0,
    "Tram": 0,
    "Taxi": 0,
    "Car as driver": 695,
    "Car as passenger": 45,
    "Truck": 5,
    "Motorbike scooter": 6,
    "Bicycle": 4,
    "Other": 0,
    "Walked only": 23,
    "Train and Bus": 10,
    "Train and Ferry": 0,
    "Train and Tram": 6,
    "Train and Car as driver": 20,
    "Train and Car as passenger": 5,
    "Train and Other": 3,
    "Bus and Ferry": 0,
    "Bus and Tram": 0,
    "Bus and Car as driver": 0,
    "Bus and Car as passenger": 3,
    "Bus and Other": 0,
    "Other two methods": 9,
    "Train and two other methods": 8,
    "Bus and two other methods excludes train": 0,
    "Other three methods": 0,
    "Worked at home": 58,
    "Did not go to work": 130
  },
  "license": "Creative Commons Attribution 2.5 Australia",
  "attribution": "Based on Australian Bureau of Statistics Data",
  "year": "2011",
  "spatial": {
    "pole": [
      -37.90128181417231,
      145.3468422174118
    ],
    "area": 165.0497608141878,
    "poly": "h|jfFksavZp@EFWPuC|Jw@?GdBRtC\\Dq@d@BBBxE^bBLh@F?DjBj@`Ad@`CjA`Bx@^P@@Fi@tCpEbA`B~Bb@p@b@|ArBfFiAl@`Fn@`@lA~BV[SiABeCk@iEo@i@kDc@g@Ai@DYUoB{AyASWNEOLmBe@eC?[aCwBmDmBsAgAy@}A{BoAMIw@w@{@qBIqAgAm@UQ]ESBOHINGX@jAKXc@fA}Ah@cEsAeA{@Uu@m@yBc@kDs@_B[DCw@k@_@kA_@SO[g@DcARqBQCEFORsBUi@GCAc@EA?cBSHg@\\iCaDy@ICy@SwBk@{Aa@As@g@PCPGAgBe@q@Qw@Sa@K_@K[rB[zBiEiAmEgAJm@NmATwAz@oGO@gHf@mBN_EZu@Ny@NG@BQiMbCc@`AwI`SiTjH_EPvA~NN@DATAFAL?^@X@B?D@VFF@B?B?@?B?LAB?BAB?@ABABAFGBANKHEDABANCBAFA\\O^ShAc@HCJBB?@?DAHCBAPKBAFCD?F@B?B@FB@@@?B???@?BADEBAFCDA@?@?B?@?@AB?PE^@h@JVBb@C^Ef@CX?\\APAJARBB?RCRK@APKHGWlBUbBvAl@ZGJBp@[fBb@_@rCPAjEfAVgBLB~A`@lAk@d@nB|Aq@j@cE?At@PhAZD@bCn@LDCNnAZFM|DbAhA^z@RLF@JFZDb@Dh@Lj@Pf@D^?JFDHFBL@NHh@Jf@D^JdA|@?FRdLsHsArJJ`@xAjAb@r@r@A\\{@p@aBBIRB@A?C?A@C?A?A?ABE?Av@iCN?vCU"
  },
  "postcode": 3160
}